polars_phonetics-0.2.0.dist-info/METADATA
polars_phonetics-0.2.0.dist-info/WHEEL
polars_phonetics-0.2.0.dist-info/licenses/LICENSE.txt
polars_phonetics.libs/libgcc_s-5b5488a6.so.1
polars_phonetics/typing.py
polars_phonetics/_internal.pyi
polars_phonetics/__init__.py
polars_phonetics/_internal.abi3.so
polars_phonetics-0.2.0.dist-info/RECORD
