Metadata-Version: 2.3
Name: polars-phonetics
Version: 0.2.0
Classifier: Development Status :: 3 - Alpha
Classifier: Intended Audience :: Developers
Classifier: Intended Audience :: Science/Research
Classifier: Intended Audience :: Information Technology
Classifier: License :: OSI Approved :: MIT License
Classifier: Natural Language :: English
Classifier: Operating System :: Microsoft :: Windows :: Windows 10
Classifier: Operating System :: Microsoft :: Windows :: Windows 11
Classifier: Operating System :: MacOS
Classifier: Operating System :: POSIX :: Linux
Classifier: Programming Language :: Rust
Classifier: Programming Language :: Python :: 3.8
Classifier: Programming Language :: Python :: 3.9
Classifier: Programming Language :: Python :: 3.10
Classifier: Programming Language :: Python :: 3.11
Classifier: Programming Language :: Python :: 3.12
Classifier: Programming Language :: Python :: Implementation :: CPython
Classifier: Programming Language :: Python :: Implementation :: PyPy
Classifier: Topic :: Software Development :: Libraries :: Python Modules
Classifier: Topic :: Text Processing :: Linguistic
Requires-Dist: polars >1.2.1
License-File: LICENSE.txt
Summary: Python Polars plugin for Rust-built phonetic algorithms
Keywords: polars,plugin,polars plugin,phonetics,phonetic algorithm
Author-email: LeCodeMinister <lecodeminister@proton.me>
Maintainer-email: LeCodeMinister <lecodeminister@proton.me>
Requires-Python: >=3.8, <3.13
Project-URL: Repository, https://github.com/LeCodeMinister/polars-phonetics
Project-URL: Documentation, https://github.com/LeCodeMinister/polars-phonetics/blob/master/README.md
Project-URL: Change Log, https://github.com/LeCodeMinister/polars-phonetics/releases
Project-URL: Issue Tracker, https://github.com/LeCodeMinister/polars-phonetics/issues
